mob_api/__init__.py
mob_api/mob_push.py
mob_api/mob_push_base.py
mob_api/mob_push_sync.py
mob_api/mob_sms.py
mob_api-0.3.1.dist-info/WHEEL
mob_api-0.3.1.dist-info/METADATA
mob_api-0.3.1.dist-info/RECORD
