Metadata-Version: 2.1
Name: mob-api
Version: 0.3.1
Summary: mob api used by QiYuTech
Author: dev
Author-email: dev@qiyutech.tech
Requires-Python: >=3.9,<4.0
Classifier: Programming Language :: Python :: 3
Classifier: Programming Language :: Python :: 3.9
Requires-Dist: aiohttp (>=3.7,<4)
Requires-Dist: pydes (>=2,<3)
Requires-Dist: requests (>=2.24,<3)
Requires-Dist: structlog (>=21,<22)
